ofjustpy/Div_TF.py
ofjustpy/HC_TF.py
ofjustpy/HC_wrappers.py
ofjustpy/MHC_types.py
ofjustpy/SHC_types.py
ofjustpy/WebPage_TF.py
ofjustpy/__init__.py
ofjustpy/app_code_introspect.py
ofjustpy/composed_SHC.py
ofjustpy/data_validator.py
ofjustpy/generate_WebPage_response_mixin.py
ofjustpy/htmlcomponents.py
ofjustpy/htmlcomponents_impl.py
ofjustpy/icons.py
ofjustpy/ofjustpy_utils.py
ofjustpy/snowsty.py
ofjustpy/svelte_safelist.py
ofjustpy/transparentsty.py
ofjustpy/ui_styles.py
ofjustpy/unsty.py
ofjustpy-1.1.2.dist-info/LICENSE
ofjustpy-1.1.2.dist-info/WHEEL
ofjustpy-1.1.2.dist-info/METADATA
ofjustpy-1.1.2.dist-info/RECORD
