Metadata-Version: 2.1
Name: ofjustpy
Version: 1.1.2
Summary: A webdev framework that enables development of full-stack webpages and app purely in Python
Maintainer-email: Kabira K <kabira@monallabs.in>
Requires-Python: >=3.11
Classifier: Development Status :: 4 - Beta
Classifier: Environment :: Web Environment
Classifier: Programming Language :: Python :: 3 :: Only
Classifier: Programming Language :: Python :: 3.11
Classifier: Operating System :: OS Independent
Classifier: Topic :: Software Development :: User Interfaces
Classifier: Intended Audience :: Developers
Classifier: Intended Audience :: Education
Classifier: Intended Audience :: Science/Research
Classifier: License :: OSI Approved :: Apache Software License
Requires-Dist: addict==2.4.0
Requires-Dist: addict-tracking-changes==1.0.6; python_version >= '3.11'
Requires-Dist: addict-tracking-changes-fixed-attributes==0.0.1; python_version >= '3.11'
Requires-Dist: aenum==3.1.15
Requires-Dist: bs4==0.0.1
Requires-Dist: cachetools==5.3.1; python_version >= '3.7'
Requires-Dist: email-validator==2.0.0.post2; python_version >= '3.7'
Requires-Dist: function-pipes==0.1.2; python_version >= '3.8' and python_version < '4.0'
Requires-Dist: ofjustpy-engine==1.1.3; python_version >= '3.11'
Requires-Dist: rpyc==5.3.1; python_version >= '3.7'
Requires-Dist: selenium==4.11.2; python_version >= '3.7'
Requires-Dist: wtforms==3.0.1; python_version >= '3.7'
Project-URL: Documentation, https://monallabs-org.github.io/ofjustpy/ofjustpy
Project-URL: Home, https://webworks.monallabs.in/ofjustpy/ofjustpy
Project-URL: Source, https://github.com/ofjustpy/ofjustpy
